{"cameraMode":{"drawMode":0,"name":"Shaded","section":"Shading Mode"},"sceneLighting":true,"audioPlay":false,"sceneViewState":{"showFog":true,"showMaterialUpdate":false,"showSkybox":true,"showFlares":true,"showImageEffects":true,"showParticleSystems":true,"showVisualEffectGraphs":true,"m_FxEnabled":true},"in2DMode":false,"pivot":{"x":1.2100512981414796,"y":5.2925238609313969,"z":-4.529175758361816},"rotation":{"x":0.21980223059654237,"y":0.3305443823337555,"z":-0.0791282206773758,"w":0.9143153429031372},"size":5.3594746589660648,"orthographic":false}